he6_cres_spec_sims/__init__.py
he6_cres_spec_sims/constants.py
he6_cres_spec_sims/experiment.py
he6_cres_spec_sims/run_simulation.py
he6_cres_spec_sims/simulation.py
he6_cres_spec_sims/daq/__init__.py
he6_cres_spec_sims/daq/frequency_domain_packet.py
he6_cres_spec_sims/simulation_blocks/DAQ.py
he6_cres_spec_sims/simulation_blocks/__init__.py
he6_cres_spec_sims/simulation_blocks/bandBuilder.py
he6_cres_spec_sims/simulation_blocks/config.py
he6_cres_spec_sims/simulation_blocks/dmTrackBuilder.py
he6_cres_spec_sims/simulation_blocks/eventBuilder.py
he6_cres_spec_sims/simulation_blocks/physics.py
he6_cres_spec_sims/simulation_blocks/segmentBuilder.py
he6_cres_spec_sims/simulation_blocks/trackBuilder.py
he6_cres_spec_sims/spec_tools/__init__.py
he6_cres_spec_sims/spec_tools/load_field_profile.py
he6_cres_spec_sims/spec_tools/trap_field_profile.py
he6_cres_spec_sims/spec_tools/beta_source/__init__.py
he6_cres_spec_sims/spec_tools/beta_source/beta_source.py
he6_cres_spec_sims/spec_tools/beta_source/beta_spectrum.py
he6_cres_spec_sims/spec_tools/beta_source/beta_spectrum_alej_OLD.py
he6_cres_spec_sims/spec_tools/beta_source/pickled_spectra/He6.json
he6_cres_spec_sims/spec_tools/beta_source/pickled_spectra/Ne19.json
he6_cres_spec_sims/spec_tools/creating_trap_geometries/__init__.py
he6_cres_spec_sims/spec_tools/creating_trap_geometries/load_default_field_profiles.py
he6_cres_spec_sims/spec_tools/creating_trap_geometries/load_field_profile.py
he6_cres_spec_sims/spec_tools/creating_trap_geometries/coil_classes/__init__.py
he6_cres_spec_sims/spec_tools/creating_trap_geometries/coil_classes/coil_form.py
he6_cres_spec_sims/spec_tools/creating_trap_geometries/coil_classes/field_profile.py
he6_cres_spec_sims/spec_tools/creating_trap_geometries/coil_classes/trap_profile.py
he6_cres_spec_sims/spec_tools/spec_calc/__init__.py
he6_cres_spec_sims/spec_tools/spec_calc/power_calc.py
he6_cres_spec_sims/spec_tools/spec_calc/spec_calc.py
he6_cres_spec_sims-0.2.0.dist-info/LICENSE
he6_cres_spec_sims-0.2.0.dist-info/METADATA
he6_cres_spec_sims-0.2.0.dist-info/WHEEL
he6_cres_spec_sims-0.2.0.dist-info/top_level.txt
he6_cres_spec_sims-0.2.0.dist-info/RECORD
