Metadata-Version: 2.1
Name: he6-cres-spec-sims
Version: 0.2.0
Summary: A package for simulating cres data.
Author-email: "William (Drew) Byron" <wbyron@uw.edu>, RJ Taylor <rjtaylo2@ncsu.edu>, Nick Buzinsky <nbuzin@uw.edu>
Project-URL: Homepage, https://github.com/Helium6CRES/he6-cres-spec-sims
Project-URL: Bug Tracker, https://github.com/Helium6CRES/he6-cres-spec-sims/issues
Classifier: Programming Language :: Python :: 3
Classifier: License :: OSI Approved :: BSD License
Classifier: Operating System :: OS Independent
Classifier: Intended Audience :: Science/Research
Classifier: Topic :: Scientific/Engineering :: Physics
Requires-Python: >=3.7.3
License-File: LICENSE
Requires-Dist: numpy >=1.20.0
Requires-Dist: pandas >=1.3.5
Requires-Dist: psycopg2-binary >=2.9.3
Requires-Dist: pyyaml >=6.0
Requires-Dist: argparse >=1.1
Requires-Dist: uproot4 >=4.0.0
Requires-Dist: scikit-learn >=1.0.1
Requires-Dist: natsort >=7.0.1
Requires-Dist: pytz >=2022.4
Requires-Dist: mpmath >=1.1.0
Requires-Dist: matplotlib >=3.5.0
Requires-Dist: ipykernel
Requires-Dist: pathlib2
Requires-Dist: scipy >=1.5
